tts_webui_valle_x-0.0.3.dist-info/licenses/LICENSE
valle_x/__init__.py
valle_x/descriptions.py
valle_x/examples.py
valle_x/launch-ui.py
valle_x/macros.py
valle_x/customs/ph.txt
valle_x/data/__init__.py
valle_x/data/collation.py
valle_x/data/datamodule.py
valle_x/data/dataset.py
valle_x/data/fbank.py
valle_x/data/input_strategies.py
valle_x/data/tokenizer.py
valle_x/images/vallex_framework.jpg
valle_x/models/__init__.py
valle_x/models/macros.py
valle_x/models/transformer.py
valle_x/models/vallex.py
valle_x/models/visualizer.py
valle_x/modules/__init__.py
valle_x/modules/activation.py
valle_x/modules/embedding.py
valle_x/modules/optim.py
valle_x/modules/scaling.py
valle_x/modules/scheduler.py
valle_x/modules/transformer.py
valle_x/nltk_data/tokenizers/punkt/.DS_Store
valle_x/nltk_data/tokenizers/punkt/README
valle_x/nltk_data/tokenizers/punkt/czech.pickle
valle_x/nltk_data/tokenizers/punkt/danish.pickle
valle_x/nltk_data/tokenizers/punkt/dutch.pickle
valle_x/nltk_data/tokenizers/punkt/english.pickle
valle_x/nltk_data/tokenizers/punkt/estonian.pickle
valle_x/nltk_data/tokenizers/punkt/finnish.pickle
valle_x/nltk_data/tokenizers/punkt/french.pickle
valle_x/nltk_data/tokenizers/punkt/german.pickle
valle_x/nltk_data/tokenizers/punkt/greek.pickle
valle_x/nltk_data/tokenizers/punkt/italian.pickle
valle_x/nltk_data/tokenizers/punkt/malayalam.pickle
valle_x/nltk_data/tokenizers/punkt/norwegian.pickle
valle_x/nltk_data/tokenizers/punkt/polish.pickle
valle_x/nltk_data/tokenizers/punkt/portuguese.pickle
valle_x/nltk_data/tokenizers/punkt/russian.pickle
valle_x/nltk_data/tokenizers/punkt/slovene.pickle
valle_x/nltk_data/tokenizers/punkt/spanish.pickle
valle_x/nltk_data/tokenizers/punkt/swedish.pickle
valle_x/nltk_data/tokenizers/punkt/turkish.pickle
valle_x/nltk_data/tokenizers/punkt/PY3/README
valle_x/nltk_data/tokenizers/punkt/PY3/czech.pickle
valle_x/nltk_data/tokenizers/punkt/PY3/danish.pickle
valle_x/nltk_data/tokenizers/punkt/PY3/dutch.pickle
valle_x/nltk_data/tokenizers/punkt/PY3/english.pickle
tts_webui_valle_x-0.0.3.dist-info/METADATA
tts_webui_valle_x-0.0.3.dist-info/WHEEL
tts_webui_valle_x-0.0.3.dist-info/top_level.txt
tts_webui_valle_x-0.0.3.dist-info/RECORD
