Metadata-Version: 2.4
Name: tts-webui.valle_x
Version: 0.0.3
Summary: Multilingual Text-to-Speech Synthesis and Voice Cloning
Author-email: Your Name <your.email@example.com>
License: MIT
Project-URL: Homepage, https://github.com/rsxdalv/VALL-E-X.git
Classifier: Development Status :: 3 - Alpha
Classifier: Intended Audience :: Developers
Classifier: License :: OSI Approved :: MIT License
Classifier: Programming Language :: Python :: 3.6
Requires-Python: >=3.6
License-File: LICENSE
Requires-Dist: soundfile
Requires-Dist: numpy
Requires-Dist: torch
Requires-Dist: torchvision
Requires-Dist: torchaudio
Requires-Dist: tokenizers
Requires-Dist: encodec
Requires-Dist: langid
Requires-Dist: wget
Requires-Dist: unidecode
Requires-Dist: pyopenjtalk-prebuilt
Requires-Dist: pypinyin
Requires-Dist: inflect
Requires-Dist: cn2an
Requires-Dist: jieba
Requires-Dist: eng_to_ipa
Requires-Dist: openai-whisper
Requires-Dist: matplotlib
Requires-Dist: nltk
Requires-Dist: sudachipy
Requires-Dist: sudachidict_core
Requires-Dist: vocos
Dynamic: license-file
